pyrb/__init__.py
pyrb/controllers/__init__.py
pyrb/controllers/api/__init__.py
pyrb/controllers/api/deps.py
pyrb/controllers/api/main.py
pyrb/controllers/cli/__init__.py
pyrb/controllers/cli/account.py
pyrb/controllers/cli/main.py
pyrb/controllers/constants.py
pyrb/enums.py
pyrb/exceptions.py
pyrb/models/__init__.py
pyrb/models/account.py
pyrb/models/order.py
pyrb/models/portfolio.py
pyrb/models/position.py
pyrb/models/price.py
pyrb/repositories/__init__.py
pyrb/repositories/account.py
pyrb/repositories/brokerages/__init__.py
pyrb/repositories/brokerages/base/__init__.py
pyrb/repositories/brokerages/base/client.py
pyrb/repositories/brokerages/base/fetcher.py
pyrb/repositories/brokerages/base/order_manager.py
pyrb/repositories/brokerages/base/portfolio.py
pyrb/repositories/brokerages/context.py
pyrb/repositories/brokerages/ebest/__init__.py
pyrb/repositories/brokerages/ebest/client.py
pyrb/repositories/brokerages/ebest/fetcher.py
pyrb/repositories/brokerages/ebest/order_manager.py
pyrb/repositories/brokerages/ebest/portfolio.py
pyrb/repositories/brokerages/factory.py
pyrb/services/__init__.py
pyrb/services/account.py
pyrb/services/rebalance.py
pyrb/services/strategy/__init__.py
pyrb/services/strategy/asset_allocate.py
pyrb/services/strategy/base.py
pyrb/services/strategy/explicit_target.py
pyrb/services/strategy/holding_portfolio.py
pyrb-0.10.9.dist-info/METADATA
pyrb-0.10.9.dist-info/WHEEL
pyrb-0.10.9.dist-info/entry_points.txt
pyrb-0.10.9.dist-info/RECORD
