Metadata-Version: 2.1
Name: pyrb
Version: 0.10.9
Summary: Python Rebalancer
Author: Minki Kim
Author-email: mingi3314@gmail.com
Requires-Python: >=3.8,<3.13
Classifier: Programming Language :: Python :: 3
Classifier: Programming Language :: Python :: 3.8
Classifier: Programming Language :: Python :: 3.9
Classifier: Programming Language :: Python :: 3.10
Classifier: Programming Language :: Python :: 3.11
Classifier: Programming Language :: Python :: 3.12
Requires-Dist: click (>=8.1.6,<9.0.0)
Requires-Dist: fastapi (>=0.109.2,<0.110.0)
Requires-Dist: pydantic (>=2.1.1,<3.0.0)
Requires-Dist: pydantic-settings (>=2.0.3,<3.0.0)
Requires-Dist: pyyaml (>=6.0.1,<7.0.0)
Requires-Dist: requests (>=2.31.0,<3.0.0)
Requires-Dist: toml (>=0.10.2,<0.11.0)
Requires-Dist: typer[all] (>=0.9.0,<0.10.0)
Requires-Dist: uvicorn[standard] (>=0.27.1,<0.28.0)
